setup.py
odoo/addons/hide_sequence_gaps_warning/README.rst
odoo/addons/hide_sequence_gaps_warning/__init__.py
odoo/addons/hide_sequence_gaps_warning/__manifest__.py
odoo/addons/hide_sequence_gaps_warning/views/account_journal_dashboard_view.xml
odoo_addon_hide_sequence_gaps_warning.egg-info/PKG-INFO
odoo_addon_hide_sequence_gaps_warning.egg-info/SOURCES.txt
odoo_addon_hide_sequence_gaps_warning.egg-info/dependency_links.txt
odoo_addon_hide_sequence_gaps_warning.egg-info/not-zip-safe
odoo_addon_hide_sequence_gaps_warning.egg-info/requires.txt
odoo_addon_hide_sequence_gaps_warning.egg-info/top_level.txt